tokopaedi/__init__.py
tokopaedi/custom_logging.py
tokopaedi/get_fingerprint.py
tokopaedi/get_product.py
tokopaedi/get_reviews.py
tokopaedi/search.py
tokopaedi/tokopaedi_types.py
tokopaedi-0.2.2.dist-info/LICENSE
tokopaedi-0.2.2.dist-info/METADATA
tokopaedi-0.2.2.dist-info/WHEEL
tokopaedi-0.2.2.dist-info/RECORD
