Metadata-Version: 2.3
Name: tokopaedi
Version: 0.2.2
Summary: A Python scraper for Tokopedia that supports filtered product search, detailed product information, and customer reviews with accurate mobile pricing and Jupyter Notebook compatibility.
License: MIT
Keywords: tokopedia,scraper,ecommerce,product,data,web-scraping,python,data-analysis,tokopedia-reviews
Author: Hilmi Azizi
Author-email: root@hilmiazizi.com
Requires-Python: >=3.8,<4.0
Classifier: Development Status :: 4 - Beta
Classifier: Intended Audience :: Developers
Classifier: License :: OSI Approved :: MIT License
Classifier: Operating System :: OS Independent
Classifier: Programming Language :: Python :: 3
Classifier: Programming Language :: Python :: 3.8
Classifier: Programming Language :: Python :: 3.9
Classifier: Programming Language :: Python :: 3.10
Classifier: Programming Language :: Python :: 3.11
Classifier: Programming Language :: Python :: 3.12
Classifier: Programming Language :: Python :: 3.13
Classifier: Topic :: Internet :: WWW/HTTP :: Indexing/Search
Classifier: Topic :: Software Development :: Libraries :: Python Modules
Requires-Dist: curl-cffi (>=0.11.4,<0.12.0)
Project-URL: Documentation, https://github.com/hilmiazizi/tokopaedi
Project-URL: Homepage, https://github.com/hilmiazizi/tokopaedi
Project-URL: Repository, https://github.com/hilmiazizi/tokopaedi
